jsonflatten/__init__.py
jsonflatten/cli.py
jsonflatten/core.py
jsonflatten-0.2.dist-info/DESCRIPTION.rst
jsonflatten-0.2.dist-info/METADATA
jsonflatten-0.2.dist-info/RECORD
jsonflatten-0.2.dist-info/WHEEL
jsonflatten-0.2.dist-info/entry_points.txt
jsonflatten-0.2.dist-info/metadata.json
jsonflatten-0.2.dist-info/top_level.txt
