Metadata-Version: 2.0
Name: jsonflatten
Version: 0.2
Summary: A JSON flattening and dataframe generation tool.
Home-page: https://github.com/json-transformations/jsonflatten
Author: Tim Phillips
Author-email: phillipstr@gmail.com
License: UNKNOWN
Platform: UNKNOWN
Classifier: License :: OSI Approved :: MIT License
Classifier: Programming Language :: Python
Classifier: Programming Language :: Python :: 3
Classifier: Topic :: Utilities
Requires-Dist: jsoncut
Requires-Dist: click (>=6.0)
